datadownloader/__init__.py
datadownloader/models.py
datadownloader/urls.py
datadownloader/views.py
datadownloader/management/__init__.py
datadownloader/management/commands/__init__.py
datadownloader/management/commands/datadownload.py
datadownloader/templates/admin/datadownloader/index.html
django_datadownloader-1.2.1.dist-info/LICENSE.txt
django_datadownloader-1.2.1.dist-info/METADATA
django_datadownloader-1.2.1.dist-info/WHEEL
django_datadownloader-1.2.1.dist-info/top_level.txt
django_datadownloader-1.2.1.dist-info/RECORD
