Metadata-Version: 2.1
Name: django-datadownloader
Version: 1.2.1
Summary: Admin interface to manage archives of db's json dumps and/or media datas
Home-page: http://pypi.python.org/pypi/django-datadownloader
Author: Philippe Lafaye
Author-email: lafaye@emencia.com
License: GNU Affero General Public License v3
Platform: UNKNOWN
Classifier: Programming Language :: Python
Classifier: License :: OSI Approved :: GNU Affero General Public License v3
Classifier: Operating System :: OS Independent
Classifier: Development Status :: 5 - Production/Stable
Classifier: Environment :: Web Environment
Classifier: Programming Language :: Python :: 2
Classifier: Programming Language :: Python :: 3
Classifier: Framework :: Django
Classifier: Framework :: Django :: 1.7
Classifier: Framework :: Django :: 1.8
Classifier: Framework :: Django :: 1.9
Classifier: Framework :: Django :: 2.0
Classifier: Framework :: Django :: 2.1
Classifier: Framework :: Django :: 2.2
Classifier: Framework :: Django :: 3.0
Classifier: Framework :: Django :: 3.1
Classifier: Intended Audience :: Developers
Classifier: Topic :: Internet :: WWW/HTTP
Classifier: Topic :: Software Development :: Libraries :: Python Modules
Requires-Dist: django-sendfile (>=0.3.11)
Requires-Dist: django (>=1.8)
Requires-Dist: dr-dump (>=1.1.5)
Requires-Dist: six
